merge/__init__.py
merge/csv_to_xlsx.py
merge/multi_csv_to_single_csv.py
merge/multi_csv_to_single_xlsx.py
digolds_dp-0.0.2.dist-info/LICENSE
digolds_dp-0.0.2.dist-info/METADATA
digolds_dp-0.0.2.dist-info/WHEEL
digolds_dp-0.0.2.dist-info/entry_points.txt
digolds_dp-0.0.2.dist-info/top_level.txt
digolds_dp-0.0.2.dist-info/RECORD
