Metadata-Version: 2.1
Name: digolds-dp
Version: 0.0.2
Summary: An easy-to-use data pipeline for data analysts
Home-page: https://github.com/digolds/dp
Author: SLZ
Author-email: founders@digolds.cn
License: UNKNOWN
Platform: UNKNOWN
Classifier: Programming Language :: Python :: 3
Classifier: License :: OSI Approved :: MIT License
Classifier: Operating System :: OS Independent
Requires-Python: >=3.6
Requires-Dist: pandas
